ultiutils/__init__.py
ultiutils/ultimain.py
ultiutils-1.1.4.dist-info/METADATA
ultiutils-1.1.4.dist-info/WHEEL
ultiutils-1.1.4.dist-info/top_level.txt
ultiutils-1.1.4.dist-info/RECORD
