Metadata-Version: 2.1
Name: ultiutils
Version: 1.1.4
Summary: utilites module to make coding in python just wayyy faster
Home-page: https://github.com/maverick-dev-55/Ultiutils
Author: toxikdevswastaken
Author-email: pypi@toxik.cf
License: MIT
Platform: UNKNOWN
Classifier: License :: OSI Approved :: MIT License
Classifier: Programming Language :: Python :: 3
Classifier: Programming Language :: Python :: 3.7
Requires-Dist: requests
